laika/__init__.py
laika/backend/__init__.py
laika/backend/git/__init__.py
laika/backend/git/tree.py
laika/cli.py
laika/commands/__init__.py
laika/commands/build.py
laika/commands/deploy.py
laika/commands/list.py
laika/commands/purge.py
laika/commands/select.py
laika/core.py
laika/git/__init__.py
laika/output.py
laika/purge.py
laika/term_color.py
laika_deploy-0.8.dist-info/entry_points.txt
laika_deploy-0.8.dist-info/LICENSE.txt
laika_deploy-0.8.dist-info/WHEEL
laika_deploy-0.8.dist-info/METADATA
laika_deploy-0.8.dist-info/RECORD
