Metadata-Version: 2.1
Name: laika-deploy
Version: 0.8
Summary: A command-line utility for easy and reliable management of manual deployments from Git repositories
Home-page: https://github.com/edudobay/laika
License: GPL-3.0
Keywords: deployment,automation,git
Author: Eduardo Dobay
Author-email: edudobay@gmail.com
Requires-Python: >=3.6,<4.0
Classifier: Development Status :: 4 - Beta
Classifier: Intended Audience :: Developers
Classifier: License :: OSI Approved :: GNU General Public License v3 (GPLv3)
Classifier: Natural Language :: English
Classifier: Operating System :: OS Independent
Classifier: Programming Language :: Python :: 3
Classifier: Programming Language :: Python :: 3.6
Classifier: Programming Language :: Python :: 3.7
Classifier: Programming Language :: Python :: 3.8
Classifier: Programming Language :: Python :: 3.9
Classifier: Topic :: Software Development :: Build Tools
Classifier: Topic :: Software Development :: Version Control :: Git
Requires-Dist: dateparser (>=0.7.0,<0.8.0)
Requires-Dist: importlib_metadata (>=2.0.0,<3.0.0); python_version < "3.8"
Requires-Dist: inquirer (>=2.7,<3.0)
Requires-Dist: pytz (>=2021.1,<2022.0)
Project-URL: Repository, https://github.com/edudobay/laika
